runrl/futures.py
runrl/config.py
runrl/models.py
runrl/http.py
runrl/client.py
runrl/exceptions.py
runrl/utils.py
runrl/__init__.py
runrl/resources/files.py
runrl/resources/base.py
runrl/resources/search.py
runrl/resources/deployments.py
runrl/resources/shared_configurations.py
runrl/resources/runs.py
runrl/resources/tools.py
runrl/resources/__init__.py
runrl/resources/validation.py
runrl/resources/api_keys.py
runrl-0.2.2.dist-info/METADATA
runrl-0.2.2.dist-info/WHEEL
runrl-0.2.2.dist-info/RECORD
