Metadata-Version: 2.1
Name: runrl
Version: 0.2.2
Summary: Official Python SDK for the RunRL API
Home-page: https://runrl.com
Author: RunRL
Author-email: support@runrl.com
License: MIT
Classifier: Programming Language :: Python
Classifier: Programming Language :: Python :: 3
Classifier: License :: OSI Approved :: MIT License
Requires-Python: >=3.9
